setup.py
bin/july3
july3/__init__.py
july3/cli.py
july3/rule.py
july3/util.py
july3.egg-info/PKG-INFO
july3.egg-info/SOURCES.txt
july3.egg-info/dependency_links.txt
july3.egg-info/top_level.txt
july3/contrib/__init__.py
july3/contrib/django.py
july3/contrib/file.py
july3/contrib/git.py
july3/contrib/mako.py
july3/contrib/mysql.py
july3/contrib/postgres.py
july3/contrib/python.py
july3/contrib/shell.py
july3/contrib/ubuntu.py
july3/contrib/django/__init__.py
spec/__init__.py
spec/test_git.py
spec/test_postgres.py
spec/test_rule.py