Metadata-Version: 1.1
Name: july3
Version: 0.0.7
Summary: Deployment automation tool
Home-page: https://github.com/youngrok/july3
Author: Youngrok Pak
Author-email: pak.youngrok@gmail.com
License: UNKNOWN
Keywords: make build deploy fabric devops
Platform: UNKNOWN
Classifier: Development Status :: 3 - Alpha
Classifier: Topic :: System :: Installation/Setup
Classifier: License :: OSI Approved :: BSD License
